KRNG/RNGs.py
KRNG/__init__.py
KRNG/__main__.py
KRNG/config.cfg
kitten_rng-1.2.1.dist-info/METADATA
kitten_rng-1.2.1.dist-info/WHEEL
kitten_rng-1.2.1.dist-info/entry_points.txt
kitten_rng-1.2.1.dist-info/top_level.txt
kitten_rng-1.2.1.dist-info/RECORD
