Metadata-Version: 2.1
Name: kitten-rng
Version: 1.2.1
Summary: an random number generator that generates its numbers based off of a
Home-page: https://github.com/SuniTheFish/Kitten-RNG
Author: Benjamin Hinchliff
Author-email: benjamin.hinchliff@gmail.com
License: MIT
Platform: UNKNOWN
Classifier: License :: OSI Approved :: MIT License
Classifier: Programming Language :: Python :: 3
Classifier: Programming Language :: Python :: 3.8
Requires-Dist: opencv-python
Requires-Dist: pafy
Requires-Dist: youtube-dl
Requires-Dist: importlib-resources
